[{"message":"عهغعه","sender":"DESKTOP-6CI06CM\n"},{"message":"gfh","sender":"DESKTOP-6CI06CM\n"},{"message":"islam mostafa","sender":"Admin"},{"message":"dfgdfg","sender":"Admin"},{"message":"dsfdsfsdf","sender":"Admin"},{"message":"dfdsfdsf","sender":"Admin"},{"message":"fdsfdsf","sender":"Admin"},{"message":"dsfdsfdsf","sender":"DESKTOP-6CI06CM\n"},{"message":"dsfdsfs","sender":"DESKTOP-6CI06CM\n"},{"message":"dsfsdf","sender":"DESKTOP-6CI06CM\n"},{"message":"dsfdsfsdf","sender":"Admin"},{"message":"hi","sender":"Admin"},{"message":"plesase","sender":"Admin"},{"message":"dsfdsfdsfdsfdsfdsfdsf","sender":"Admin"},{"message":"fgfdgfdgfdgfdgfdgfdgfdgfdgfdgfdgfdgfdg","sender":"Admin"},{"message":"dsdfdsf","sender":"DESKTOP-6CI06CM\n"},{"message":"dfsfsdfdsfdsfdslkf;dslf\\","sender":"Admin"},{"message":"dsfdsfdslfds","sender":"Admin"},{"message":"dsdfdsfdsfdsf","sender":"DESKTOP-6CI06CM\n"},{"message":"dsfdsfdslfds","sender":"Admin"},{"message":"xzccczx","sender":"Admin"},{"message":"xzccczxdfdsf","sender":"Admin"},{"message":"xzccczxdfdsf","sender":"Admin"},{"message":"sdfsdf","sender":"Admin"},{"message":"Gi","sender":"Admin"},{"message":"Gitff","sender":"Admin"},{"message":"sddsvdsvsd","sender":"DESKTOP-491CVUA\r\n"},{"message":"Hi ","sender":"Admin"},{"message":"I hope you are will","sender":"Admin"},{"message":"adadad","sender":"DESKTOP-491CVUA\r\n"},{"message":"adadad","sender":"DESKTOP-491CVUA\r\n"},{"message":"adadad","sender":"DESKTOP-491CVUA\r\n"},{"message":"sadasdasd","sender":"DESKTOP-491CVUA\r\n"},{"message":"Hi","sender":"Admin"},{"message":"hi back admin ","sender":"DESKTOP-491CVUA\r\n"},{"message":"fghgfhgfh","sender":"DESKTOP-6CI06CM\n"},{"message":"fghgfhgfh","sender":"DESKTOP-6CI06CM\n"},{"message":"dfdsf","sender":"DESKTOP-6CI06CM\n"},{"message":"fghfgh","sender":"DESKTOP-6CI06CM\n"},"hi islam",{"sender":"Admin","message":"mn,nm,"},{"sender":"Admin","message":"vnbvnbvn"},{"message":"dsfdsfsdf","sender":"DESKTOP-6CI06CM\n"},{"message":"dsfsdfsd","sender":"DESKTOP-6CI06CM\n"},{"sender":"Admin","message":"cdsc"},{"sender":"Admin","message":"csdcds"},{"sender":"Admin","message":"cass"},{"sender":"Admin","message":"cscasc"},{"sender":"Admin","message":"csacsac"},{"message":"sacascasc","sender":"DESKTOP-6CI06CM\n"},{"message":"cscascscacsac","sender":"DESKTOP-6CI06CM\n"},{"message":"hgfhgfh","sender":"DESKTOP-6CI06CM\n"},{"sender":"Admin","message":"fgdfg"},{"sender":"Admin","message":"fdgfdgd"},{"sender":"Admin","message":"fgdfgfdg"},{"sender":"Admin","message":"hgjghj"},{"message":"dgfgfdg","sender":"DESKTOP-6CI06CM\n"},{"message":"sdadsad","sender":"DESKTOP-6CI06CM\n"},{"message":"hi admin","sender":"DESKTOP-6CI06CM\n"},{"sender":"Admin","message":"hi client\n"},{"sender":"Admin","message":"hgghnhg"},{"message":"dsfdsfsdf","sender":"DESKTOP-6CI06CM\n"},{"message":"عهغعه","sender":"DESKTOP-6CI06CM\n"},{"sender":"Admin","message":"gfhfghfghf"},{"sender":"Admin","message":"dsdsfsdf"},{"message":"dscdscsd","sender":"DESKTOP-6CI06CM\n"},{"sender":"Admin","message":"dsfdsfdsf"},{"message":";l;lk;k","sender":"DESKTOP-6CI06CM\n"}]